[
    {
        "name": "John",
        "constraints": {
            "closeToWhiteboard": true
        }
    },
    {
        "name": "Bob",
        "constraints": {
            "closeToWhiteboard": true
        }
    },
    {
        "name": "Alice",
        "constraints": {
            "closeToWhiteboard": true
        }
    },
    {
        "name": "Charlie",
        "constraints": {
            "closeToWhiteboard": true
        }
    },
    {
        "name": "David",
        "constraints": {
            "closeToWhiteboard": true
        }
    },
    {
        "name": "Eve",
        "constraints": {}
    },
    {
        "name": "Frank",
        "constraints": {
            "canNotSitNextTo": "Eve"
        }
    },
    {
        "name": "Grace",
        "constraints": {}
    },
    {
        "name": "Heidi",
        "constraints": {}
    }
]
